{
  "builders": [{
    "type": "amazon-ebs",
    "communicator": "winrm",
    "winrm_username": "packer",
    "winrm_password": "D@rj33l1n9",
    "winrm_port": 5985,
    "windows_password_timeout": "30m",
    "region": "{{ user `region` }}",
    "source_ami": "{{ user `source_ami` }}",
    "instance_type": "m3.medium",
    "ami_name": "win-2012-r2 {{ timestamp }}",
    "user_data_file": "userdata.txt",
    "access_key": "{{ user `access_key` }}",
    "secret_key": "{{ user `secret_key` }}",
    "vpc_id":	"{{ user `vpc_id` }}",
    "subnet_id": "{{ user `subnet_id` }}",
    "security_group_id": "{{ user `security_group` }}",
    "ami_block_device_mappings": [{
      "device_name": "/dev/sda1",
      "delete_on_termination": true
    }],
    "launch_block_device_mappings": [{
      "device_name": "/dev/sda1",
      "delete_on_termination": true
    }],
    "run_tags": {
      "Name": "Packer Builder (Windows 2012 R2)"
    },
    "tags": {
      "Name": "Windows 2012 R2"
    }
  }],
  "provisioners": [{
    "type": "powershell",
    "inline": [
      "iex ((new-object net.webclient).DownloadString('https://chocolatey.org/install.ps1'))",
      "choco install -y 7zip"
    ]
  }],
  "variables": {
    "access_key": "",
    "secret_key": "",
    "source_ami": "",
    "vpc_id": "",
    "subnet_id": "" ,
    "security_group": "" ,
    "region": ""
  }
}
